tes/__init__.py
tes/ess.py
indomaret-1.2.0.dist-info/METADATA
indomaret-1.2.0.dist-info/WHEEL
indomaret-1.2.0.dist-info/entry_points.txt
indomaret-1.2.0.dist-info/top_level.txt
indomaret-1.2.0.dist-info/RECORD
